{"cameraMode":{"drawMode":0,"name":"Shaded","section":"Shading Mode"},"sceneLighting":true,"audioPlay":false,"sceneViewState":{"showFog":true,"showMaterialUpdate":false,"showSkybox":true,"showFlares":true,"showImageEffects":true,"showParticleSystems":true,"showVisualEffectGraphs":true,"m_FxEnabled":true},"in2DMode":false,"pivot":{"x":-14.044845581054688,"y":9.535308837890625,"z":7.922800064086914},"rotation":{"x":0.15576212108135224,"y":-0.7312527894973755,"z":0.17802715301513673,"w":0.6397967338562012},"size":68.28070068359375,"orthographic":false}